{
  "categories": {
    "gaming_consoles": {
      "name": "Gaming Consoles",
      "description": "Latest gaming consoles from PlayStation",
      "image": "/images/products/gaming-console.jpg",
      "subCategories": [
        "PS5",
        "PS4",
        "Controllers",
        "Games",
        "Gaming Accessories"
      ]
    },
    "mobile_phones": {
      "name": "Mobile Phones",
      "description": "Latest smartphones and accessories",
      "image": "/images/products/S25.jpg",
      "subCategories": [
        "Apple",
        "Samsung",
        "Google",
        "OnePlus",
        "Phone Accessories"
      ]
    },
    "televisions": {
      "name": "Televisions",
      "description": "High-end smart TVs for ultimate entertainment",
      "image": "/images/products/samsung-qn.jpg",
      "subCategories": [
        "OLED TVs",
        "QLED TVs",
        "LED TVs",
        "Smart TVs",
        "TV Mounts"
      ]
    },
    "gaming_accessories": {
      "name": "Gaming Accessories",
      "description": "Essential gaming peripherals and accessories",
      "image": "/images/products/ps5-1.jpg",
      "subCategories": [
        "Headsets",
        "Gaming Chairs",
        "Storage",
        "Cables",
        "Controller Charging"
      ]
    }
  },
  "products": [
    {
      "id": "ps5-001",
      "name": "PlayStation 5 Digital Edition",
      "category": "gaming_consoles",
      "subCategory": "PS5",
      "price": 399.99,
      "description": "Next-gen gaming console featuring lightning-fast loading, deeper immersion with haptic feedback, and stunning 4K graphics.",
      "features": [
        "825GB SSD Storage",
        "4K-TV Gaming",
        "HDR Technology",
        "3D Audio",
        "Ray Tracing Support"
      ],
      "images": ["/images/products/ps5-2.jpg", "/images/products/ps5-3.jpg"],
      "dimensions": {
        "width": 39,
        "height": 26,
        "depth": 9.2,
        "unit": "cm"
      },
      "materials": ["Premium plastic", "Advanced cooling system"],
      "inStock": true,
      "leadTime": "1-2 weeks",
      "rating": 4.9,
      "reviews": 245
    },
    {
      "id": "ps5-002",
      "name": "DualSense Wireless Controller",
      "category": "gaming_consoles",
      "subCategory": "Controllers",
      "price": 69.99,
      "description": "Revolutionary controller featuring haptic feedback and adaptive triggers for PS5.",
      "features": [
        "Haptic Feedback",
        "Adaptive Triggers",
        "Built-in Microphone",
        "USB-C Charging",
        "Create Button"
      ],
      "images": [
        "/images/products/dualsense.jpg",
        "/images/products/gaming-pad.jpg"
      ],
      "dimensions": {
        "width": 16,
        "height": 10,
        "depth": 6,
        "unit": "cm"
      },
      "materials": ["High-grade plastic", "Rechargeable battery"],
      "inStock": true,
      "leadTime": "1 week",
      "rating": 4.8,
      "reviews": 189
    },
    {
      "id": "ps4-001",
      "name": "PlayStation 4 Pro",
      "category": "gaming_consoles",
      "subCategory": "PS4",
      "price": 299.99,
      "description": "4K gaming console with enhanced graphics and performance for immersive gaming experiences.",
      "features": [
        "4K Gaming",
        "1TB Storage",
        "HDR Support",
        "Boost Mode",
        "Enhanced Graphics"
      ],
      "images": ["/images/products/ps4-1.jpg", "/images/products/ps4-2.jpg"],
      "dimensions": {
        "width": 32.7,
        "height": 5.5,
        "depth": 29.5,
        "unit": "cm"
      },
      "materials": ["Premium plastic", "Metal chassis"],
      "inStock": true,
      "leadTime": "1 week",
      "rating": 4.7,
      "reviews": 320
    },
    {
      "id": "phone-001",
      "name": "Samsung Galaxy S23 Ultra",
      "category": "mobile_phones",
      "subCategory": "Samsung",
      "price": 1199.99,
      "description": "Premium flagship smartphone with advanced camera system and S Pen functionality.",
      "features": [
        "200MP Camera",
        "S Pen included",
        "5G Capability",
        "6.8\" Dynamic AMOLED",
        "5000mAh Battery"
      ],
      "images": ["/images/products/s23.jpg", "/images/products/S25.jpg"],
      "dimensions": {
        "width": 7.8,
        "height": 16.3,
        "depth": 0.89,
        "unit": "cm"
      },
      "materials": ["Gorilla Glass", "Aluminum frame"],
      "inStock": true,
      "leadTime": "1-2 weeks",
      "rating": 4.9,
      "reviews": 156
    },
    {
      "id": "tv-001",
      "name": "LG C2 65\" OLED TV",
      "category": "televisions",
      "subCategory": "OLED TVs",
      "price": 1999.99,
      "description": "Premium OLED TV with stunning picture quality and gaming features.",
      "features": [
        "4K OLED Display",
        "120Hz Refresh Rate",
        "HDMI 2.1",
        "Dolby Vision",
        "Game Optimizer"
      ],
      "images": ["/images/products/lg-c2.jpg", "/images/products/lg-c2.jpg"],
      "dimensions": {
        "width": 144.9,
        "height": 83.9,
        "depth": 5.1,
        "unit": "cm"
      },
      "materials": ["OLED Panel", "Premium stand"],
      "inStock": true,
      "leadTime": "2-3 weeks",
      "rating": 4.8,
      "reviews": 89
    },
    {
      "id": "acc-001",
      "name": "PS5 Pulse 3D Wireless Headset",
      "category": "gaming_accessories",
      "subCategory": "Headsets",
      "price": 99.99,
      "description": "Official PS5 wireless headset designed for 3D Audio with dual noise-cancelling microphones.",
      "features": [
        "3D Audio Support",
        "Dual Microphones",
        "Wireless Adapter",
        "Rechargeable Battery",
        "Quick Controls"
      ],
      "images": ["/images/products/pulse-1.jpg", "/images/products/pulse.jpg"],
      "dimensions": {
        "width": 18,
        "height": 22,
        "depth": 9,
        "unit": "cm"
      },
      "materials": ["Premium plastic", "Cushioned earpads"],
      "inStock": true,
      "leadTime": "1 week",
      "rating": 4.7,
      "reviews": 134
    },
    {
      "id": "phone-002",
      "name": "iPhone 14 Pro Max",
      "category": "mobile_phones",
      "subCategory": "Apple",
      "price": 1099.99,
      "description": "Apple's flagship smartphone with Dynamic Island and advanced camera system.",
      "features": [
        "48MP Main Camera",
        "Dynamic Island",
        "A16 Bionic Chip",
        "ProMotion Display",
        "5G Capability"
      ],
      "images": [
        "/images/products/iphone-14.jpg",
        "/images/products/iphone-14-1.jpg"
      ],
      "dimensions": {
        "width": 7.7,
        "height": 16.0,
        "depth": 0.78,
        "unit": "cm"
      },
      "materials": ["Ceramic Shield", "Stainless Steel"],
      "inStock": true,
      "leadTime": "1-2 weeks",
      "rating": 4.9,
      "reviews": 203
    },
    {
      "id": "tv-002",
      "name": "Samsung QN90B Neo QLED 4K",
      "category": "televisions",
      "subCategory": "QLED TVs",
      "price": 1799.99,
      "description": "Premium QLED TV with Mini LED technology and gaming features.",
      "features": [
        "Neo QLED Technology",
        "4K 120Hz",
        "HDR10+",
        "Gaming Hub",
        "Object Tracking Sound"
      ],
      "images": [
        "/images/products/samsung-qn.jpg",
        "/images/products/samsung-qn-1.jpg"
      ],
      "dimensions": {
        "width": 123.5,
        "height": 71.2,
        "depth": 2.6,
        "unit": "cm"
      },
      "materials": ["QLED Panel", "Premium stand"],
      "inStock": true,
      "leadTime": "2-3 weeks",
      "rating": 4.8,
      "reviews": 76
    }
  ]
}
